sparsesolvers-0.8.8.data/purelib/sparsesolvers/__init__.py
sparsesolvers-0.8.8.data/purelib/sparsesolvers/binding.cpython-35m-x86_64-linux-gnu.so
sparsesolvers-0.8.8.data/purelib/sparsesolvers/libopenblas.x86-64-HASWELL.so
sparsesolvers-0.8.8.data/purelib/sparsesolvers/libopenblas.x86-64-NEHALEM.so
sparsesolvers-0.8.8.dist-info/top_level.txt
sparsesolvers-0.8.8.dist-info/WHEEL
sparsesolvers-0.8.8.dist-info/METADATA
sparsesolvers-0.8.8.dist-info/RECORD
