Metadata-Version: 2.1
Name: sparsesolvers
Version: 0.8.8
Summary: High performance ℓ₁-minimization solvers
Home-page: https://github.com/rayglover-ibm/sparse-solvers
Author: IBM
Author-email: gh@rayglover.net
License: Apache 2.0
Keywords: compressive sensing,sparsity,homotopy,blas
Platform: UNKNOWN
Classifier: Development Status :: 4 - Beta
Classifier: Intended Audience :: Developers
Classifier: Intended Audience :: Science/Research
Classifier: License :: OSI Approved :: Apache Software License
Classifier: Programming Language :: Python :: 2
Classifier: Programming Language :: Python :: 2.7
Classifier: Programming Language :: Python :: 3
Classifier: Programming Language :: Python :: 3.5
Classifier: Programming Language :: Python :: 3.6
Classifier: Topic :: Scientific/Engineering
Classifier: Topic :: Scientific/Engineering :: Mathematics
Classifier: Topic :: Software Development
Classifier: Topic :: Software Development :: Libraries
Classifier: Topic :: Software Development :: Libraries :: Python Modules
Requires-Dist: numpy (>=0.11)
Requires-Dist: wheel (>=0.27)
